toolkit/__init__.py
toolkit/auth/__init__.py
toolkit/auth/context.py
toolkit/client/__init__.py
toolkit/client/auth.py
toolkit/client/base.py
toolkit/db/__init__.py
toolkit/db/alembic/__init__.py
toolkit/db/alembic/cli.py
toolkit/db/alembic/controller.py
toolkit/db/cli.py
toolkit/db/models.py
toolkit/db/query.py
toolkit/db/sqla.py
toolkit/db/types.py
toolkit/exceptions/__init__.py
toolkit/exceptions/base.py
toolkit/exceptions/no_traceback.py
toolkit/exceptions/registry.py
toolkit/exceptions/serviceexception.py
toolkit/manager/__init__.py
toolkit/manager/client.py
toolkit/manager/models.py
toolkit/minio/__init__.py
toolkit/minio/client.py
toolkit/py.typed
toolkit/token.py
toolkit/utils.py
scse_toolkit-0.14.0.dist-info/METADATA
scse_toolkit-0.14.0.dist-info/WHEEL
scse_toolkit-0.14.0.dist-info/RECORD
